llama_index/readers/json/__init__.py
llama_index/readers/json/base.py
llama_index_readers_json-0.4.2.dist-info/METADATA
llama_index_readers_json-0.4.2.dist-info/WHEEL
llama_index_readers_json-0.4.2.dist-info/licenses/LICENSE
llama_index_readers_json-0.4.2.dist-info/RECORD
