Metadata-Version: 2.4
Name: llama-index-readers-json
Version: 0.4.2
Summary: llama-index readers json integration
Author-email: Your Name <you@example.com>
Maintainer: yisding
License-Expression: MIT
License-File: LICENSE
Requires-Python: <4.0,>=3.9
Requires-Dist: llama-index-core<0.15,>=0.13.0
